{
    "MySql": {
        "domain": "https://jensir1024.com",
        "username": "gengchangzhou",
        "password": "gcz@#2022",
        "path_markdown": [
            "D:/CodeWorkSpace/blog/markdown/jensir1024/md/DataBase/MySql"
        ],
        "post_metadata": {
            "category": ["DataBase","MySql"],
            "tag": ["MySql","MySql性能优化","数据库性能优化"],
            "status": "publish"
        },
        "path_legacy_json": "/config/legacy"
    },
    "Java基础": {
        "domain": "https://jensir1024.com",
        "username": "gengchangzhou",
        "password": "gcz@#2022",
        "path_markdown": [
            "D:/CodeWorkSpace/blog/markdown/jensir1024/md/Java/Java基础"
        ],
        "post_metadata": {
            "category": ["Java","Java基础"],
            "tag": ["Java","BigDecimal","BigDecimal","BigDecimal详解"],
            "status": "publish"
        },
        "path_legacy_json": "/config/legacy"
    },
    "Http": {
        "domain": "https://jensir1024.com",
        "username": "gengchangzhou",
        "password": "gcz@#2022",
        "path_markdown": [
            "D:/CodeWorkSpace/blog/markdown/jensir1024/md/Network/Http"
        ],
        "post_metadata": {
            "category": ["Network","Http"],
            "tag": ["Network","Http","Http状态码","Http响应"],
            "status": "publish"
        },
        "path_legacy_json": "/config/legacy"
    },
    "OkHttp": {
        "domain": "https://jensir1024.com",
        "username": "gengchangzhou",
        "password": "gcz@#2022",
        "path_markdown": [
            "D:/CodeWorkSpace/blog/markdown/jensir1024/md/Java/OkHttp"
        ],
        "post_metadata": {
            "category": ["Java","OkHttp"],
            "tag": ["Java","OkHttp","OkHttp基础使用","OkHttp用法"],
            "status": "publish"
        },
        "path_legacy_json": "/config/legacy"
    },
    "SpringCloud": {
        "domain": "https://jensir1024.com",
        "username": "gengchangzhou",
        "password": "gcz@#2022",
        "path_markdown": [
            "D:/CodeWorkSpace/blog/markdown/jensir1024/md/Java/SpringCloud"
        ],
        "post_metadata": {
            "category": ["Java","SpringCloud"],
            "tag": ["SpringCloud","SpringCloud介绍","SpringCloud简介"],
            "status": "publish"
        },
        "path_legacy_json": "/config/legacy"
    },
    "Nginx": {
        "domain": "https://jensir1024.com",
        "username": "gengchangzhou",
        "password": "gcz@#2022",
        "path_markdown": [
            "D:/CodeWorkSpace/blog/markdown/jensir1024/md/Nginx"
        ],
        "post_metadata": {
            "category": ["Nginx"],
            "tag": ["Nginx","Nginx介绍"],
            "status": "publish"
        },
        "path_legacy_json": "/config/legacy"
    }

}